{
  "packages/core": {
    "lines": 89.95,
    "branches": 74.04,
    "functions": 91.33,
    "statements": 87.66
  },
  "packages/graph": {
    "lines": 95.69,
    "branches": 81.44,
    "functions": 96.73,
    "statements": 94.23
  },
  "packages/cli": {
    "lines": 80.54,
    "branches": 67.24,
    "functions": 84.28,
    "statements": 79.88
  },
  "packages/orchestrator": {
    "lines": 76.49,
    "branches": 63.03,
    "functions": 78.37,
    "statements": 75.2
  },
  "packages/eslint-plugin": {
    "lines": 94.67,
    "branches": 85.57,
    "functions": 99.08,
    "statements": 92.27
  },
  "packages/linter-gen": {
    "lines": 89.39,
    "branches": 79.54,
    "functions": 100,
    "statements": 90.07
  },
  "packages/types": {
    "lines": 100,
    "branches": 100,
    "functions": 100,
    "statements": 100
  }
}
