{
  "packages/core": {
    "lines": 89.85,
    "branches": 73.87,
    "functions": 91.14,
    "statements": 87.5
  },
  "packages/graph": {
    "lines": 95.8,
    "branches": 80.85,
    "functions": 97.17,
    "statements": 94.2
  },
  "packages/cli": {
    "lines": 81.26,
    "branches": 67.59,
    "functions": 85.45,
    "statements": 80.58
  },
  "packages/orchestrator": {
    "lines": 72.96,
    "branches": 60.67,
    "functions": 75.67,
    "statements": 71.94
  },
  "packages/eslint-plugin": {
    "lines": 94.67,
    "branches": 85.57,
    "functions": 99.08,
    "statements": 92.27
  },
  "packages/linter-gen": {
    "lines": 89.39,
    "branches": 79.54,
    "functions": 100,
    "statements": 90.07
  },
  "packages/types": {
    "lines": 100,
    "branches": 100,
    "functions": 100,
    "statements": 100
  }
}
