{
  "$schema": "https://design-tokens.github.io/community-group/format/",
  "color": {
    "primary": {
      "$value": "#2563eb",
      "$type": "color",
      "$description": "Primary brand color"
    },
    "primary-contrast": {
      "$value": "#ffffff",
      "$type": "color",
      "$description": "Text on primary"
    },
    "secondary": {
      "$value": "#64748b",
      "$type": "color",
      "$description": "Secondary text and borders"
    },
    "error": {
      "$value": "#dc2626",
      "$type": "color",
      "$description": "Error state"
    }
  },
  "typography": {
    "display": {
      "$value": {
        "fontFamily": "Instrument Serif",
        "fontSize": "3rem",
        "fontWeight": 400,
        "lineHeight": 1.1
      },
      "$type": "typography"
    },
    "body": {
      "$value": {
        "fontFamily": "Geist",
        "fontSize": "1rem",
        "fontWeight": 400,
        "lineHeight": 1.6
      },
      "$type": "typography"
    }
  },
  "spacing": {
    "scale": {
      "$value": ["0.25rem", "0.5rem", "1rem", "1.5rem", "2rem", "3rem", "4rem"],
      "$type": "dimension"
    }
  }
}
