{
  "schemaVersion": 2,
  "sessionDir": ".harness/sessions/changes--unified-project-roadmap--proposal",
  "specPath": "docs/changes/unified-project-roadmap/proposal.md",
  "currentState": "DONE",
  "currentPhase": 5,
  "phases": [
    {
      "name": "Core Types and Parser",
      "complexity": "low",
      "complexityOverride": null,
      "planPath": "docs/plans/2026-03-21-roadmap-core-types-parser-plan.md",
      "status": "complete"
    },
    {
      "name": "MCP Tool — CRUD Operations",
      "complexity": "medium",
      "complexityOverride": null,
      "planPath": "docs/plans/2026-03-21-roadmap-mcp-tool-crud-plan.md",
      "status": "complete"
    },
    {
      "name": "Skill — Interactive Creation",
      "complexity": "medium",
      "complexityOverride": null,
      "planPath": "docs/plans/2026-03-21-roadmap-skill-creation-plan.md",
      "status": "complete"
    },
    {
      "name": "Sync Engine",
      "complexity": "medium",
      "complexityOverride": null,
      "planPath": "docs/plans/2026-03-21-roadmap-sync-engine-plan.md",
      "status": "complete"
    },
    {
      "name": "Integration Hooks",
      "complexity": "low",
      "complexityOverride": null,
      "planPath": "docs/plans/2026-03-21-roadmap-integration-hooks-plan.md",
      "status": "complete"
    },
    {
      "name": "Skill — Remaining Commands",
      "complexity": "low",
      "complexityOverride": null,
      "planPath": "docs/plans/2026-03-21-roadmap-remaining-commands-plan.md",
      "status": "complete"
    }
  ],
  "retryBudget": {
    "maxAttempts": 3,
    "currentTask": null
  },
  "decisions": [
    "Phase 1 plan approved for execution",
    "Phase 2 plan approved for execution",
    "Phase 3 plan approved for execution",
    "Phase 4 plan approved for execution",
    "Phase 5 plan approved for execution",
    "Phase 6 plan approved for execution"
  ],
  "history": [
    {
      "phase": 0,
      "name": "Core Types and Parser",
      "startedAt": "2026-03-21T08:10:00Z",
      "completedAt": "2026-03-21T08:17:00Z",
      "tasksCompleted": 6,
      "retriesUsed": 0,
      "verificationPassed": true,
      "reviewFindings": { "blocking": 0, "warning": 0, "note": 0 }
    },
    {
      "phase": 1,
      "name": "MCP Tool — CRUD Operations",
      "startedAt": "2026-03-21T08:20:00Z",
      "completedAt": "2026-03-21T08:29:00Z",
      "tasksCompleted": 7,
      "retriesUsed": 0,
      "verificationPassed": true,
      "reviewFindings": { "blocking": 0, "warning": 0, "note": 0 }
    },
    {
      "phase": 2,
      "name": "Skill — Interactive Creation",
      "startedAt": "2026-03-21T08:32:00Z",
      "completedAt": "2026-03-21T08:40:00Z",
      "tasksCompleted": 5,
      "retriesUsed": 0,
      "verificationPassed": true,
      "reviewFindings": { "blocking": 0, "warning": 0, "note": 0 }
    },
    {
      "phase": 3,
      "name": "Sync Engine",
      "startedAt": "2026-03-21T08:42:00Z",
      "completedAt": "2026-03-21T12:12:00Z",
      "tasksCompleted": 7,
      "retriesUsed": 0,
      "verificationPassed": true,
      "reviewFindings": { "blocking": 0, "warning": 0, "note": 0 }
    },
    {
      "phase": 4,
      "name": "Integration Hooks",
      "startedAt": "2026-03-21T12:15:00Z",
      "completedAt": "2026-03-21T12:25:00Z",
      "tasksCompleted": 5,
      "retriesUsed": 0,
      "verificationPassed": true,
      "reviewFindings": { "blocking": 0, "warning": 0, "note": 0 }
    },
    {
      "phase": 5,
      "name": "Skill — Remaining Commands",
      "startedAt": "2026-03-21T12:28:00Z",
      "completedAt": "2026-03-21T12:35:00Z",
      "tasksCompleted": 4,
      "retriesUsed": 0,
      "verificationPassed": true,
      "reviewFindings": { "blocking": 0, "warning": 0, "note": 0 }
    }
  ]
}
